{
    "Characteristics": {
        "Length": [
            56,
            "m"
        ],
        "Width": [
            8,
            "m"
        ],
        "Height": [
            "5.5",
            "m"
        ],
        "Pylon Length": [
            12,
            "m"
        ],
        "Pylon Count": [
            3
        ],
        "Pylon Breakdown": [
            3,
            0,
            0
        ]
    },
    "Description": {
        "0": "The most powerful bomber used by the Avingarde.",
        "1": "The size of these ships was impressive and the various refits enabled them to be used for many differnt missions and kept the spaceframe alive long after the class itself was repaced."
    }
}